furnace/VERSION
furnace/__init__.py
furnace/config.py
furnace/context.py
furnace/libc.py
furnace/pid1.py
furnace/utils.py
furnace/version.py
furnace-0.0.10.dist-info/LICENSE.txt
furnace-0.0.10.dist-info/METADATA
furnace-0.0.10.dist-info/WHEEL
furnace-0.0.10.dist-info/top_level.txt
furnace-0.0.10.dist-info/RECORD
