Metadata-Version: 2.1
Name: furnace
Version: 0.0.10
Summary: A lightweight pure-python container implementation
Home-page: https://github.com/balabit/furnace
License: UNKNOWN
Keywords: containers containerization
Platform: UNKNOWN
Classifier: Development Status :: 4 - Beta
Classifier: Intended Audience :: Developers
Classifier: License :: OSI Approved :: GNU Lesser General Public License v2 or later (LGPLv2+)
Classifier: Operating System :: POSIX :: Linux
Classifier: Programming Language :: Python :: 3
Classifier: Topic :: System
Requires-Python: >=3.6
Provides-Extra: dev
Requires-Dist: anybadge (==1.9.0) ; extra == 'dev'
Requires-Dist: attrs (==22.2.0) ; extra == 'dev'
Requires-Dist: autopep8 (==2.0.0) ; extra == 'dev'
Requires-Dist: coverage (==6.2) ; extra == 'dev'
Requires-Dist: flake8 (==5.0.4) ; extra == 'dev'
Requires-Dist: importlib-metadata (==4.2.0) ; extra == 'dev'
Requires-Dist: iniconfig (==1.1.1) ; extra == 'dev'
Requires-Dist: mccabe (==0.7.0) ; extra == 'dev'
Requires-Dist: packaging (==21.3) ; extra == 'dev'
Requires-Dist: pluggy (==1.0.0) ; extra == 'dev'
Requires-Dist: py (==1.11.0) ; extra == 'dev'
Requires-Dist: pycodestyle (==2.9.1) ; extra == 'dev'
Requires-Dist: pyflakes (==2.5.0) ; extra == 'dev'
Requires-Dist: pyparsing (==3.0.9) ; extra == 'dev'
Requires-Dist: pytest (==7.0.1) ; extra == 'dev'
Requires-Dist: pytest-cov (==2.12.1) ; extra == 'dev'
Requires-Dist: toml (==0.10.2) ; extra == 'dev'
Requires-Dist: tomli (==1.2.3) ; extra == 'dev'
Requires-Dist: typing-extensions (==4.1.1) ; extra == 'dev'
Requires-Dist: zipp (==3.6.0) ; extra == 'dev'
